frmbase/__init__.py
frmbase/checkimports.py
frmbase/dfpipeline.py
frmbase/dfverify.py
frmbase/expt.py
frmbase/fitter/AbstractFitter.py
frmbase/fitter/RobustFitter.py
frmbase/fitter/__init__.py
frmbase/fitter/cnlsf.py
frmbase/fitter/legendre.py
frmbase/fitter/lsf.py
frmbase/fitter/lsf2d.py
frmbase/fitter/modlsf.py
frmbase/fitter/nlsf.py
frmbase/fitter/readme.md
frmbase/fitter/sphharm.py
frmbase/fitter/test_sph.py
frmbase/fixeddict.py
frmbase/flogger.py
frmbase/funcimport.py
frmbase/gapfill.py
frmbase/meta.py
frmbase/parmap.py
frmbase/plateau.py
frmbase/support.py
frmbase/textio.py
frmbase/tstools.py
frmbase-0.2.0.dist-info/METADATA
frmbase-0.2.0.dist-info/WHEEL
frmbase-0.2.0.dist-info/RECORD
