Metadata-Version: 2.1
Name: frmbase
Version: 0.2.0
Summary: 
Author: Fergal
Author-email: fergal.mullally@gmail.com
Requires-Python: >=3.8,<4.0
Classifier: Programming Language :: Python :: 3
Classifier: Programming Language :: Python :: 3.8
Classifier: Programming Language :: Python :: 3.9
Classifier: Programming Language :: Python :: 3.10
Classifier: Programming Language :: Python :: 3.11
Requires-Dist: colorama
Requires-Dist: gitpython
Requires-Dist: ipdb
Requires-Dist: numpy
Requires-Dist: pandas
Requires-Dist: scipy
Requires-Dist: tqdm
